esbmc_ai_addon_template/__about__.py
esbmc_ai_addon_template/__init__.py
esbmc_ai_addon_template/template_command.py
esbmc_ai_addon_template-0.0.2.dist-info/METADATA
esbmc_ai_addon_template-0.0.2.dist-info/WHEEL
esbmc_ai_addon_template-0.0.2.dist-info/licenses/LICENSE
esbmc_ai_addon_template-0.0.2.dist-info/RECORD
